nordic_bot/__init__.py
nordic_bot/constant.py
nordic_bot/main.py
nordic_bot/modals.py
nordic_bot/ntbot.py
nordic_bot/test.py
nordic_bot/timerole.py
nordic_bot/utility.py
nordic_bot/views.py
nordic_bot-1.0.4.dist-info/METADATA
nordic_bot-1.0.4.dist-info/WHEEL
nordic_bot-1.0.4.dist-info/top_level.txt
nordic_bot-1.0.4.dist-info/RECORD
